LICENSE.txt
README.md
setup.cfg
setup.py
packagefortesting/test.py
packagefortesting.egg-info/PKG-INFO
packagefortesting.egg-info/SOURCES.txt
packagefortesting.egg-info/dependency_links.txt
packagefortesting.egg-info/top_level.txt