Metadata-Version: 2.1
Name: packagefortesting
Version: 0.1
Summary: for testing purposes
License-File: LICENSE.txt
